py3sac/LICENSE.md
py3sac/__init__.py
py3sac/sac.py
py3sac/setup.py
py3sac-1.1.5.data/scripts/sac2asc
py3sac-1.1.5.dist-info/licenses/LICENSE.md
py3sac-1.1.5.dist-info/METADATA
py3sac-1.1.5.dist-info/WHEEL
py3sac-1.1.5.dist-info/top_level.txt
py3sac-1.1.5.dist-info/RECORD
