Metadata-Version: 2.4
Name: py3sac
Version: 1.1.5
Summary: Python tools to use SAC files and execute commands using the SAC program  (Seismic Analysis Code).
Home-page: 
License: 3-clause BSD 2.0
Classifier: License :: OSI Approved :: BSD License
Classifier: Programming Language :: Python :: 3
License-File: LICENSE.md
Requires-Dist: pysacio
Requires-Dist: py3toolset
Dynamic: classifier
Dynamic: description
Dynamic: license
Dynamic: license-file
Dynamic: requires-dist
Dynamic: summary
